CMakeLists.txt
COPYING
MANIFEST.in
Makefile.in
README.rst
config.h.in
configure
setup.cfg
setup.py
setup.py.in
check_deps/Makefile
check_deps/test.cc
docs/Makefile
docs/conf.py
docs/conf.py.in
docs/index.rst
docs/references.bib
docs/_build/html/pyplots/tajd.py
docs/pages/changes.rst
docs/pages/deprecated_overview.rst
docs/pages/lifetimes.rst
docs/pages/summstats.rst
docs/pages/treesequences.rst
docs/pages/vmatrix.rst
docs/pages/zreferences.rst
docs/pyplots/tajd.py
libsequence/CMakeLists.txt
libsequence/__init__.py
libsequence/__main__.py
libsequence/citations.py
libsequence/msprime.py
libsequence/msstats_cli.py
libsequence/src/_libsequence.cc
libsequence/src/fst.cc
libsequence/src/omega_max.cc
libsequence/src/polytable.cc
libsequence/src/summstats.cc
libsequence/src/variant_matrix.cc
libsequence/src/windows_cpp.cc
libsequence/src/libsequence/Sequence/AlignStream.hpp
libsequence/src/libsequence/Sequence/Alignment.hpp
libsequence/src/libsequence/Sequence/AlleleCountMatrix.hpp
libsequence/src/libsequence/Sequence/Clustalw.hpp
libsequence/src/libsequence/Sequence/CodonTable.hpp
libsequence/src/libsequence/Sequence/Comeron95.hpp
libsequence/src/libsequence/Sequence/Comparisons.hpp
libsequence/src/libsequence/Sequence/ComplementBase.hpp
libsequence/src/libsequence/Sequence/CountingOperators.hpp
libsequence/src/libsequence/Sequence/FST.hpp
libsequence/src/libsequence/Sequence/Fasta.hpp
libsequence/src/libsequence/Sequence/Grantham.hpp
libsequence/src/libsequence/Sequence/GranthamWeights.hpp
libsequence/src/libsequence/Sequence/HKA.hpp
libsequence/src/libsequence/Sequence/Hudson2001.hpp
libsequence/src/libsequence/Sequence/Kimura80.hpp
libsequence/src/libsequence/Sequence/NonOwningCapsules.hpp
libsequence/src/libsequence/Sequence/PathwayHelper.hpp
libsequence/src/libsequence/Sequence/PolyFunctional.hpp
libsequence/src/libsequence/Sequence/PolySIM.hpp
libsequence/src/libsequence/Sequence/PolySNP.hpp
libsequence/src/libsequence/Sequence/PolySNPimpl.hpp
pylibseq.egg-info/PKG-INFO
pylibseq.egg-info/SOURCES.txt
pylibseq.egg-info/dependency_links.txt
pylibseq.egg-info/not-zip-safe
pylibseq.egg-info/requires.txt
pylibseq.egg-info/top_level.txt
