Metadata-Version: 1.1
Name: pylibseq
Version: 0.2.3
Summary: Python interface to libsequence.
Home-page: http://molpopgen.github.io/pylibseq
Author: Kevin Thornton
Author-email: krthornt@uci.edu
License: GPL >= 3
Platform: UNKNOWN
Classifier: Intended Audience :: Science/Research
Classifier: Topic :: Scientific/Engineering :: Bio-Informatics
Classifier: License :: OSI Approved :: GNU General Public License v3 or later (GPLv3+)
Requires: pybind11
Requires: numpy
Provides: pylibseq
Obsoletes: none
